django_observability/__init__.py
django_observability/async_support.py
django_observability/config.py
django_observability/django_integration.py
django_observability/exceptions.py
django_observability/logging.py
django_observability/metrics.py
django_observability/middleware.py
django_observability/tracing.py
django_observability/utils.py
django_observability-0.1.0.dist-info/licenses/LICENSE
django_observability-0.1.0.dist-info/METADATA
django_observability-0.1.0.dist-info/WHEEL
django_observability-0.1.0.dist-info/top_level.txt
django_observability-0.1.0.dist-info/RECORD
