Metadata-Version: 2.4
Name: django-observability
Version: 0.1.0
Summary: A Django middleware for observability with OpenTelemetry, Prometheus, and structured logging
Home-page: https://github.com/mahdighadiriii/django-observability
Author: Mahdi Ghadiri
Author-email: Mahdi Ghadiri <mahdighadiriafzal@gmail.com>
License: MIT License
Classifier: Programming Language :: Python :: 3
Classifier: Programming Language :: Python :: 3.8
Classifier: Programming Language :: Python :: 3.9
Classifier: Programming Language :: Python :: 3.10
Classifier: Programming Language :: Python :: 3.11
Classifier: Programming Language :: Python :: 3.12
Classifier: License :: OSI Approved :: MIT License
Classifier: Operating System :: OS Independent
Classifier: Framework :: Django
Classifier: Framework :: Django :: 3.2
Classifier: Framework :: Django :: 4.0
Classifier: Framework :: Django :: 4.1
Classifier: Framework :: Django :: 4.2
Classifier: Framework :: Django :: 5.0
Classifier: Framework :: Django :: 5.1
Classifier: Framework :: Django :: 5.2
Classifier: Topic :: Software Development :: Libraries :: Python Modules
Classifier: Topic :: System :: Monitoring
Requires-Python: >=3.10
License-File: LICENSE
Requires-Dist: django<6.0,>=3.2
Requires-Dist: setuptools<81
Requires-Dist: opentelemetry-api==1.21.0
Requires-Dist: opentelemetry-sdk==1.21.0
Requires-Dist: opentelemetry-instrumentation-django==0.42b0
Requires-Dist: opentelemetry-instrumentation-psycopg2==0.42b0
Requires-Dist: opentelemetry-instrumentation-redis==0.42b0
Requires-Dist: opentelemetry-instrumentation-requests==0.42b0
Requires-Dist: opentelemetry-exporter-otlp-proto-grpc==1.21.0
Requires-Dist: opentelemetry-exporter-jaeger-thrift==1.21.0
Requires-Dist: opentelemetry-exporter-zipkin==1.21.0
Requires-Dist: prometheus-client<1.0.0,>=0.17.0
Requires-Dist: structlog<26.0.0,>=23.1.0
Requires-Dist: psycopg2-binary>=2.9.3
Requires-Dist: redis>=4.0.0
Provides-Extra: dev
Requires-Dist: pytest>=7.4.0; extra == "dev"
Requires-Dist: pytest-django>=4.8.0; extra == "dev"
Requires-Dist: pytest-cov>=4.1.0; extra == "dev"
Requires-Dist: pytest-asyncio>=0.21.1; extra == "dev"
Requires-Dist: flake8>=6.0.0; extra == "dev"
Requires-Dist: black>=23.7.0; extra == "dev"
Requires-Dist: isort>=5.12.0; extra == "dev"
Requires-Dist: mypy>=1.5.1; extra == "dev"
Requires-Dist: requests-mock>=1.11.0; extra == "dev"
Requires-Dist: pre-commit>=3.3.3; extra == "dev"
Requires-Dist: ruff>=0.4.3; extra == "dev"
Requires-Dist: opentelemetry-exporter-jaeger-thrift==1.21.0; extra == "dev"
Provides-Extra: sqlite
Requires-Dist: opentelemetry-instrumentation-sqlite3==0.42b0; extra == "sqlite"
Provides-Extra: mysql
Requires-Dist: opentelemetry-instrumentation-mysql==0.42b0; extra == "mysql"
Provides-Extra: memcached
Requires-Dist: opentelemetry-instrumentation-memcached==0.42b0; extra == "memcached"
Dynamic: author
Dynamic: home-page
Dynamic: license-file
Dynamic: requires-python
